pynamic/__init__.py
pynamic/core.py
pynamic/dynamic_variables.py
pynamic/extras.py
pynamic/parser.py
pynamic/proxy.py
pynamic/token.py
pynamic/utils.py
pynamic-0.3.0.dist-info/LICENSE
pynamic-0.3.0.dist-info/METADATA
pynamic-0.3.0.dist-info/WHEEL
pynamic-0.3.0.dist-info/top_level.txt
pynamic-0.3.0.dist-info/RECORD
